yodine_data/__init__.py
yodine_data/inventory.py
yodine_data/pathfinder.py
yodine_data/plugin.py
yodine_data/version.py
yodine_data/assets/sprites/a_shitty_wallaby.png
yodine_data/assets/sprites/ball.png
yodine_data/assets/sprites/barrel.png
yodine_data/assets/sprites/branch1.png
yodine_data/assets/sprites/branch2.png
yodine_data/assets/sprites/grass1.png
yodine_data/assets/sprites/grass2.png
yodine_data/assets/sprites/leaves1.png
yodine_data/assets/sprites/leaves2.png
yodine_data/assets/sprites/sign.png
yodine_data/assets/tiles/dirt-floor.png
yodine_data/assets/tiles/floor.png
yodine_data/assets/tiles/ice.png
yodine_data/assets/tiles/metal-floor.png
yodine_data/assets/tiles/metal-wall.png
yodine_data/assets/tiles/stone-floor.png
yodine_data/assets/tiles/wall.png
yodine_data-0.3.2.dist-info/METADATA
yodine_data-0.3.2.dist-info/WHEEL
yodine_data-0.3.2.dist-info/entry_points.txt
yodine_data-0.3.2.dist-info/top_level.txt
yodine_data-0.3.2.dist-info/RECORD
