Metadata-Version: 2.1
Name: yodine-data
Version: 0.3.2
Summary: All the assets, entities and levels that come with Yodine (the game). Note there can be multiple games for Yodine (the engine).
Home-page: UNKNOWN
Author: Gustavo6046
License: MIT
Platform: UNKNOWN
Classifier: Programming Language :: Python
Classifier: Programming Language :: Python :: 3
Classifier: Programming Language :: Python :: 3.5
Classifier: Programming Language :: Python :: Implementation :: CPython
Classifier: Programming Language :: Python :: Implementation :: PyPy
Requires-Python: >=3.5.0
Requires-Dist: yodine-data
